<?xml version="1.0" encoding="utf-8"?>
<annotation>
   <folder>own</folder>
   <filename>101</filename>
   <size>
      <width>1920</width>
      <height>1090</height>
      <depth>3</depth>
   </size>
   <segmented>0</segmented>
   <object>
      <name>boat</name>
      <pose>Unspecified</pose>
      <truncated>0</truncated>
      <difficult>0</difficult>
      <bndbox>
         <xmax>740.75</xmax>
         <ymax>541</ymax>
         <xmin>99</xmin>
         <ymin>46.5</ymin>
      </bndbox>
   </object>
   <object>
      <name>boat</name>
      <pose>Unspecified</pose>
      <truncated>0</truncated>
      <difficult>0</difficult>
      <bndbox>
         <xmax>398.75</xmax>
         <ymax>547</ymax>
         <xmin>177</xmin>
         <ymin>52.5</ymin>
      </bndbox>
   </object>
   <object>
      <name>boat</name>
      <pose>Unspecified</pose>
      <truncated>0</truncated>
      <difficult>0</difficult>
      <bndbox>
         <xmax>130.25</xmax>
         <ymax>536.5</ymax>
         <xmin>261</xmin>
         <ymin>66</ymin>
      </bndbox>
   </object>
   <object>
      <name>boat</name>
      <pose>Unspecified</pose>
      <truncated>0</truncated>
      <difficult>0</difficult>
      <bndbox>
         <xmax>256.25</xmax>
         <ymax>496</ymax>
         <xmin>117</xmin>
         <ymin>73.5</ymin>
      </bndbox>
   </object>
</annotation>