<?xml version="1.0" encoding="utf-8"?>
<annotation>
   <folder>own</folder>
   <filename>114</filename>
   <size>
      <width>1920</width>
      <height>1090</height>
      <depth>3</depth>
   </size>
   <segmented>0</segmented>
   <object>
      <name>boat</name>
      <pose>Unspecified</pose>
      <truncated>0</truncated>
      <difficult>0</difficult>
      <bndbox>
         <xmax>62.75</xmax>
         <ymax>509.5</ymax>
         <xmin>589.5</xmin>
         <ymin>100.5</ymin>
      </bndbox>
   </object>
   <object>
      <name>boat</name>
      <pose>Unspecified</pose>
      <truncated>0</truncated>
      <difficult>0</difficult>
      <bndbox>
         <xmax>748.25</xmax>
         <ymax>482.5</ymax>
         <xmin>136.5</xmin>
         <ymin>73.5</ymin>
      </bndbox>
   </object>
   <object>
      <name>boat</name>
      <pose>Unspecified</pose>
      <truncated>0</truncated>
      <difficult>0</difficult>
      <bndbox>
         <xmax>910.25</xmax>
         <ymax>493</ymax>
         <xmin>96</xmin>
         <ymin>57</ymin>
      </bndbox>
   </object>
   <object>
      <name>boat</name>
      <pose>Unspecified</pose>
      <truncated>0</truncated>
      <difficult>0</difficult>
      <bndbox>
         <xmax>1193.75</xmax>
         <ymax>470.5</ymax>
         <xmin>94.5</xmin>
         <ymin>45</ymin>
      </bndbox>
   </object>
</annotation>