<?xml version="1.0" encoding="utf-8"?>
<annotation>
   <folder>own</folder>
   <filename>132</filename>
   <size>
      <width>1920</width>
      <height>1090</height>
      <depth>3</depth>
   </size>
   <segmented>0</segmented>
   <object>
      <name>boat</name>
      <pose>Unspecified</pose>
      <truncated>0</truncated>
      <difficult>0</difficult>
      <bndbox>
         <xmax>1664.75</xmax>
         <ymax>478</ymax>
         <xmin>90</xmin>
         <ymin>60</ymin>
      </bndbox>
   </object>
   <object>
      <name>boat</name>
      <pose>Unspecified</pose>
      <truncated>0</truncated>
      <difficult>0</difficult>
      <bndbox>
         <xmax>1765.25</xmax>
         <ymax>452.5</ymax>
         <xmin>151.5</xmin>
         <ymin>85.5</ymin>
      </bndbox>
   </object>
   <object>
      <name>boat</name>
      <pose>Unspecified</pose>
      <truncated>0</truncated>
      <difficult>0</difficult>
      <bndbox>
         <xmax>79.25</xmax>
         <ymax>550</ymax>
         <xmin>166.5</xmin>
         <ymin>132</ymin>
      </bndbox>
   </object>
   <object>
      <name>boat</name>
      <pose>Unspecified</pose>
      <truncated>0</truncated>
      <difficult>0</difficult>
      <bndbox>
         <xmax>236.75</xmax>
         <ymax>530.5</ymax>
         <xmin>168</xmin>
         <ymin>124.5</ymin>
      </bndbox>
   </object>
   <object>
      <name>boat</name>
      <pose>Unspecified</pose>
      <truncated>0</truncated>
      <difficult>0</difficult>
      <bndbox>
         <xmax>650.75</xmax>
         <ymax>521.5</ymax>
         <xmin>187.5</xmin>
         <ymin>87</ymin>
      </bndbox>
   </object>
   <object>
      <name>boat</name>
      <pose>Unspecified</pose>
      <truncated>0</truncated>
      <difficult>0</difficult>
      <bndbox>
         <xmax>878.75</xmax>
         <ymax>536.5</ymax>
         <xmin>91.5</xmin>
         <ymin>46.5</ymin>
      </bndbox>
   </object>
   <object>
      <name>boat</name>
      <pose>Unspecified</pose>
      <truncated>0</truncated>
      <difficult>0</difficult>
      <bndbox>
         <xmax>389.75</xmax>
         <ymax>512.5</ymax>
         <xmin>178.5</xmin>
         <ymin>130.5</ymin>
      </bndbox>
   </object>
</annotation>