<?xml version="1.0" encoding="utf-8"?>
<annotation>
   <folder>own</folder>
   <filename>166</filename>
   <size>
      <width>1920</width>
      <height>1090</height>
      <depth>3</depth>
   </size>
   <segmented>0</segmented>
   <object>
      <name>boat</name>
      <pose>Unspecified</pose>
      <truncated>0</truncated>
      <difficult>0</difficult>
      <bndbox>
         <xmin>1498.25</xmin>
         <ymin>491.5</ymin>
         <xmax>1786.25</xmax>
         <ymax>575.5</ymax>
      </bndbox>
   </object>
   <object>
      <name>boat</name>
      <pose>Unspecified</pose>
      <truncated>0</truncated>
      <difficult>0</difficult>
      <bndbox>
         <xmin>1145.75</xmin>
         <ymin>479.5</ymin>
         <xmax>1478.75</xmax>
         <ymax>575.5</ymax>
      </bndbox>
   </object>
   <object>
      <name>boat</name>
      <pose>Unspecified</pose>
      <truncated>0</truncated>
      <difficult>0</difficult>
      <bndbox>
         <xmin>844.25</xmin>
         <ymin>440.5</ymin>
         <xmax>1088.75</xmax>
         <ymax>560.5</ymax>
      </bndbox>
   </object>
   <object>
      <name>boat</name>
      <pose>Unspecified</pose>
      <truncated>0</truncated>
      <difficult>0</difficult>
      <bndbox>
         <xmin>680.75</xmin>
         <ymin>500.5</ymin>
         <xmax>815.75</xmax>
         <ymax>551.5</ymax>
      </bndbox>
   </object>
   <object>
      <name>boat</name>
      <pose>Unspecified</pose>
      <truncated>0</truncated>
      <difficult>0</difficult>
      <bndbox>
         <xmin>616.25</xmin>
         <ymin>506.5</ymin>
         <xmax>685.25</xmax>
         <ymax>545.5</ymax>
      </bndbox>
   </object>
   <object>
      <name>boat</name>
      <pose>Unspecified</pose>
      <truncated>0</truncated>
      <difficult>0</difficult>
      <bndbox>
         <xmin>466.25</xmin>
         <ymin>506.5</ymin>
         <xmax>553.25</xmax>
         <ymax>550.0</ymax>
      </bndbox>
   </object>
</annotation>