<?xml version="1.0" encoding="utf-8"?>
<annotation>
   <folder>own</folder>
   <filename>35</filename>
   <size>
      <width>1920</width>
      <height>1090</height>
      <depth>3</depth>
   </size>
   <segmented>0</segmented>
   <object>
      <name>boat</name>
      <pose>Unspecified</pose>
      <truncated>0</truncated>
      <difficult>0</difficult>
      <bndbox>
         <xmax>1786</xmax>
         <ymax>596</ymax>
         <xmin>133</xmin>
         <ymin>163</ymin>
      </bndbox>
   </object>
   <object>
      <name>boat</name>
      <pose>Unspecified</pose>
      <truncated>0</truncated>
      <difficult>0</difficult>
      <bndbox>
         <xmax>1445</xmax>
         <ymax>313</ymax>
         <xmin>270</xmin>
         <ymin>388</ymin>
      </bndbox>
   </object>
   <object>
      <name>boat</name>
      <pose>Unspecified</pose>
      <truncated>0</truncated>
      <difficult>0</difficult>
      <bndbox>
         <xmax>1282</xmax>
         <ymax>600</ymax>
         <xmin>168</xmin>
         <ymin>65</ymin>
      </bndbox>
   </object>
   <object>
      <name>boat</name>
      <pose>Unspecified</pose>
      <truncated>0</truncated>
      <difficult>0</difficult>
      <bndbox>
         <xmax>1176</xmax>
         <ymax>590</ymax>
         <xmin>157</xmin>
         <ymin>72</ymin>
      </bndbox>
   </object>
   <object>
      <name>boat</name>
      <pose>Unspecified</pose>
      <truncated>0</truncated>
      <difficult>0</difficult>
      <bndbox>
         <xmax>1100</xmax>
         <ymax>594</ymax>
         <xmin>90</xmin>
         <ymin>41</ymin>
      </bndbox>
   </object>
   <object>
      <name>boat</name>
      <pose>Unspecified</pose>
      <truncated>0</truncated>
      <difficult>0</difficult>
      <bndbox>
         <xmax>1060</xmax>
         <ymax>603</ymax>
         <xmin>35</xmin>
         <ymin>22</ymin>
      </bndbox>
   </object>
</annotation>