<annotation>
<folder>
COCO2014pascalformat
</folder>
<filename>
000000438629.jpg
</filename>
<source>
<database>
COCO2014pascalformat
</database>
</source>
<size>
<width>
640
</width>
<height>
640
</height>
<depth>
3
</depth>
</size>
<segmented>
0
</segmented>
</object>
</object>
</object>
</object>
</object>
<object>
<name>boat</name>
<bndbox>
<xmin>
123
</xmin>
<ymin>
438
</ymin>
<xmax>
145
</xmax>
<ymax>
446
</ymax>
</bndbox>
<truncated>
0
</truncated>
<difficult>
0
</difficult>
</object>
<object>
<name>boat</name>
<bndbox>
<xmin>
186
</xmin>
<ymin>
444
</ymin>
<xmax>
197
</xmax>
<ymax>
450
</ymax>
</bndbox>
<truncated>
0
</truncated>
<difficult>
0
</difficult>
</object>
</object>
</object>
</annotation>